test/__init__.py
torchtree/__init__.py
torchtree/_version.py
torchtree/core/__init__.py
torchtree/core/core.py
torchtree/trees/__init__.py
torchtree/trees/browser.py
TorchTree_nightly-0.0.3.post1.dist-info/LICENSE.md
TorchTree_nightly-0.0.3.post1.dist-info/METADATA
TorchTree_nightly-0.0.3.post1.dist-info/WHEEL
TorchTree_nightly-0.0.3.post1.dist-info/top_level.txt
TorchTree_nightly-0.0.3.post1.dist-info/RECORD
