Metadata-Version: 2.1
Name: TorchTree-nightly
Version: 0.0.3.post1
Summary: Python tree manager. 
Home-page: https://github.com/JuanFMontesinos/TorchTree
Author: Juan Montesinos
Author-email: juanfelipe.montesinos@upf.edu
License: UNKNOWN
Platform: UNKNOWN
Classifier: Programming Language :: Python :: 3
